recommender/__init__.py
recommender/recommender.py
recommender/static/css/introjs.css
recommender/static/css/recommender.css
recommender/static/css/recommenderstudio.css
recommender/static/css/tooltipster.bundle.min.css
recommender/static/js/src/cats.js
recommender/static/js/src/recommender.js
recommender/static/js/src/recommenderstudio.js
recommender/static/js/src/tooltipster.bundle.min.js
recommender/templates/recommender.html
recommender/templates/recommenderstudio.html
recommender/translations/config.yaml
recommender_xblock-3.1.0.dist-info/licenses/LICENSE
recommender_xblock-3.1.0.dist-info/METADATA
recommender_xblock-3.1.0.dist-info/WHEEL
recommender_xblock-3.1.0.dist-info/entry_points.txt
recommender_xblock-3.1.0.dist-info/top_level.txt
recommender_xblock-3.1.0.dist-info/RECORD
