Metadata-Version: 2.4
Name: recommender-xblock
Version: 3.1.0
Summary: recommender XBlock
Home-page: https://github.com/openedx/RecommenderXBlock
Author: edX
Author-email: oscm@edx.org
License: AGPL 3.0
Keywords: edx recommender
Classifier: Development Status :: 4 - Beta
Classifier: Intended Audience :: Developers
Classifier: License :: OSI Approved :: GNU Affero General Public License v3 or later (AGPLv3+)
Classifier: Natural Language :: English
Classifier: Programming Language :: Python :: 3
Classifier: Programming Language :: Python :: 3.11
Classifier: Programming Language :: Python :: 3.12
License-File: LICENSE
Dynamic: author
Dynamic: author-email
Dynamic: classifier
Dynamic: description
Dynamic: home-page
Dynamic: keywords
Dynamic: license
Dynamic: license-file
Dynamic: summary
